{
    "5a16bb52fcdbcb001a3b00dc": {
        "ItemID": "5a16bb52fcdbcb001a3b00dc",
        "Name": "helmet_wilcox_skull_lock",
        "AllowADS": true,
        "LoyaltyLevel": 2,
        "ReloadSpeedMulti": 1,
        "BlocksMouth": false,
        "speedPenaltyPercent": 0,
        "mousePenalty": 0,
        "weaponErgonomicPenalty": 0,
        "TemplateType": "gear"
    },
    "5b4329075acfc400153b78ff": {
        "ItemID": "5b4329075acfc400153b78ff",
        "Name": "item_equipment_head_pompon",
        "AllowADS": true,
        "LoyaltyLevel": 1,
        "ReloadSpeedMulti": 1,
        "BlocksMouth": false,
        "speedPenaltyPercent": 0,
        "mousePenalty": 0,
        "weaponErgonomicPenalty": 0,
        "TemplateType": "gear"
    },
    "5a43943586f77416ad2f06e2": {
        "ItemID": "5a43943586f77416ad2f06e2",
        "Name": "cap_dedmoroz",
        "AllowADS": true,
        "LoyaltyLevel": 2,
        "ReloadSpeedMulti": 1,
        "BlocksMouth": false,
        "speedPenaltyPercent": 0,
        "mousePenalty": 0,
        "weaponErgonomicPenalty": 0,
        "TemplateType": "gear"
    },
    "5aa2b89be5b5b0001569311f": {
        "ItemID": "5aa2b89be5b5b0001569311f",
        "Name": "cap_mhs",
        "AllowADS": true,
        "LoyaltyLevel": 1,
        "ReloadSpeedMulti": 1,
        "BlocksMouth": false,
        "speedPenaltyPercent": 0,
        "mousePenalty": 0,
        "weaponErgonomicPenalty": 0,
        "TemplateType": "gear"
    },
    "5f60e784f2bcbb675b00dac7": {
        "ItemID": "5f60e784f2bcbb675b00dac7",
        "Name": "item_equipment_head_beret_od",
        "AllowADS": true,
        "LoyaltyLevel": 2,
        "ReloadSpeedMulti": 1,
        "BlocksMouth": false,
        "speedPenaltyPercent": 0,
        "mousePenalty": 0,
        "weaponErgonomicPenalty": 0,
        "TemplateType": "gear"
    },
    "5f99418230835532b445e954": {
        "ItemID": "5f99418230835532b445e954",
        "Name": "item_equipment_cap_r2",
        "AllowADS": true,
        "LoyaltyLevel": 1,
        "ReloadSpeedMulti": 1,
        "BlocksMouth": false,
        "speedPenaltyPercent": 0,
        "mousePenalty": 0,
        "weaponErgonomicPenalty": 0,
        "TemplateType": "gear"
    },
    "5aa2b9ede5b5b000137b758b": {
        "ItemID": "5aa2b9ede5b5b000137b758b",
        "Name": "hats_cowboy",
        "AllowADS": true,
        "LoyaltyLevel": 2,
        "ReloadSpeedMulti": 1,
        "BlocksMouth": false,
        "speedPenaltyPercent": 0,
        "mousePenalty": 0,
        "weaponErgonomicPenalty": 0,
        "TemplateType": "gear"
    },
    "5ab8f20c86f7745cdb629fb2": {
        "ItemID": "5ab8f20c86f7745cdb629fb2",
        "Name": "hats_skihat",
        "AllowADS": true,
        "LoyaltyLevel": 2,
        "ReloadSpeedMulti": 1,
        "BlocksMouth": false,
        "speedPenaltyPercent": 0,
        "mousePenalty": 0,
        "weaponErgonomicPenalty": 0,
        "TemplateType": "gear"
    },
    "5b40e5e25acfc4001a599bea": {
        "ItemID": "5b40e5e25acfc4001a599bea",
        "Name": "item_equipment_head_bear_black",
        "AllowADS": true,
        "LoyaltyLevel": 2,
        "ReloadSpeedMulti": 1,
        "BlocksMouth": false,
        "speedPenaltyPercent": 0,
        "mousePenalty": 0,
        "weaponErgonomicPenalty": 0,
        "TemplateType": "gear"
    },
    "603619720ca681766b6a0fc4": {
        "ItemID": "603619720ca681766b6a0fc4",
        "Name": "item_equipment_head_military2_brown",
        "AllowADS": true,
        "LoyaltyLevel": 1,
        "ReloadSpeedMulti": 1,
        "BlocksMouth": false,
        "speedPenaltyPercent": 0,
        "mousePenalty": 0,
        "weaponErgonomicPenalty": 0,
        "TemplateType": "gear"
    },
    "5aa2b87de5b5b00016327c25": {
        "ItemID": "5aa2b87de5b5b00016327c25",
        "Name": "cap_BEAR",
        "AllowADS": true,
        "LoyaltyLevel": 2,
        "ReloadSpeedMulti": 1,
        "BlocksMouth": false,
        "speedPenaltyPercent": 0,
        "mousePenalty": 0,
        "weaponErgonomicPenalty": 0,
        "TemplateType": "gear"
    },
    "59e770f986f7742cbe3164ef": {
        "ItemID": "59e770f986f7742cbe3164ef",
        "Name": "army_cap",
        "AllowADS": true,
        "LoyaltyLevel": 1,
        "ReloadSpeedMulti": 1,
        "BlocksMouth": false,
        "speedPenaltyPercent": 0,
        "mousePenalty": 0,
        "weaponErgonomicPenalty": 0,
        "TemplateType": "gear"
    },
    "5f60e7788adaa7100c3adb49": {
        "ItemID": "5f60e7788adaa7100c3adb49",
        "Name": "item_equipment_head_beret_blue",
        "AllowADS": true,
        "LoyaltyLevel": 1,
        "ReloadSpeedMulti": 1,
        "BlocksMouth": false,
        "speedPenaltyPercent": 0,
        "mousePenalty": 0,
        "weaponErgonomicPenalty": 0,
        "TemplateType": "gear"
    },
    "5b43271c5acfc432ff4dce65": {
        "ItemID": "5b43271c5acfc432ff4dce65",
        "Name": "item_equipment_head_bandana",
        "AllowADS": true,
        "LoyaltyLevel": 1,
        "ReloadSpeedMulti": 1,
        "BlocksMouth": false,
        "speedPenaltyPercent": 0,
        "mousePenalty": 0,
        "weaponErgonomicPenalty": 0,
        "TemplateType": "gear"
    },
    "61c18db6dfd64163ea78fbb4": {
        "ItemID": "61c18db6dfd64163ea78fbb4",
        "Name": "item_equipment_head_leather_cap",
        "AllowADS": true,
        "LoyaltyLevel": 1,
        "ReloadSpeedMulti": 1,
        "BlocksMouth": false,
        "speedPenaltyPercent": 0,
        "mousePenalty": 0,
        "weaponErgonomicPenalty": 0,
        "TemplateType": "gear"
    },
    "572b7fa124597762b472f9d2": {
        "ItemID": "572b7fa124597762b472f9d2",
        "Name": "knitcap",
        "AllowADS": true,
        "LoyaltyLevel": 1,
        "ReloadSpeedMulti": 1,
        "BlocksMouth": false,
        "speedPenaltyPercent": 0,
        "mousePenalty": 0,
        "weaponErgonomicPenalty": 0,
        "TemplateType": "gear"
    },
    "572b7d8524597762b472f9d1": {
        "ItemID": "572b7d8524597762b472f9d1",
        "Name": "cap",
        "AllowADS": true,
        "LoyaltyLevel": 1,
        "ReloadSpeedMulti": 1,
        "BlocksMouth": false,
        "speedPenaltyPercent": 0,
        "mousePenalty": 0,
        "weaponErgonomicPenalty": 0,
        "TemplateType": "gear"
    },
    "5aa2a7e8e5b5b00016327c16": {
        "ItemID": "5aa2a7e8e5b5b00016327c16",
        "Name": "cap_USEC",
        "AllowADS": true,
        "LoyaltyLevel": 2,
        "ReloadSpeedMulti": 1,
        "BlocksMouth": false,
        "speedPenaltyPercent": 0,
        "mousePenalty": 0,
        "weaponErgonomicPenalty": 0,
        "TemplateType": "gear"
    },
    "5f60e6403b85f6263c14558c": {
        "ItemID": "5f60e6403b85f6263c14558c",
        "Name": "item_equipment_head_beret_blk",
        "AllowADS": true,
        "LoyaltyLevel": 3,
        "ReloadSpeedMulti": 1,
        "BlocksMouth": false,
        "speedPenaltyPercent": 0,
        "mousePenalty": 0,
        "weaponErgonomicPenalty": 0,
        "TemplateType": "gear"
    },
    "60361b5a9a15b10d96792291": {
        "ItemID": "60361b5a9a15b10d96792291",
        "Name": "item_equipment_head_military2_ucp",
        "AllowADS": true,
        "LoyaltyLevel": 1,
        "ReloadSpeedMulti": 1,
        "BlocksMouth": false,
        "speedPenaltyPercent": 0,
        "mousePenalty": 0,
        "weaponErgonomicPenalty": 0,
        "TemplateType": "gear"
    },
    "5d96141523f0ea1b7f2aacab": {
        "ItemID": "5d96141523f0ea1b7f2aacab",
        "Name": "item_equipment_head_doorkicker",
        "AllowADS": true,
        "LoyaltyLevel": 4,
        "ReloadSpeedMulti": 1,
        "BlocksMouth": false,
        "speedPenaltyPercent": 0,
        "mousePenalty": 0,
        "weaponErgonomicPenalty": 0,
        "TemplateType": "gear"
    },
    "5b4327aa5acfc400175496e0": {
        "ItemID": "5b4327aa5acfc400175496e0",
        "Name": "item_equipment_head_panama",
        "AllowADS": true,
        "LoyaltyLevel": 2,
        "ReloadSpeedMulti": 1,
        "BlocksMouth": false,
        "speedPenaltyPercent": 0,
        "mousePenalty": 0,
        "weaponErgonomicPenalty": 0,
        "TemplateType": "gear"
    },
    "60a7acf20c5cb24b01346648": {
        "ItemID": "60a7acf20c5cb24b01346648",
        "Name": "item_equipment_head_tagillacap",
        "AllowADS": true,
        "LoyaltyLevel": 4,
        "ReloadSpeedMulti": 1,
        "BlocksMouth": false,
        "speedPenaltyPercent": 0,
        "mousePenalty": 0,
        "weaponErgonomicPenalty": 0,
        "TemplateType": "gear"
    },
    "5aa2ba19e5b5b00014028f4e": {
        "ItemID": "5aa2ba19e5b5b00014028f4e",
        "Name": "hats_fleece",
        "AllowADS": true,
        "LoyaltyLevel": 3,
        "ReloadSpeedMulti": 1,
        "BlocksMouth": false,
        "speedPenaltyPercent": 0,
        "mousePenalty": 0,
        "weaponErgonomicPenalty": 0,
        "TemplateType": "gear"
    },
    "59e7708286f7742cbd762753": {
        "ItemID": "59e7708286f7742cbd762753",
        "Name": "ushanka",
        "AllowADS": true,
        "LoyaltyLevel": 1,
        "ReloadSpeedMulti": 1,
        "BlocksMouth": false,
        "speedPenaltyPercent": 0,
        "mousePenalty": 0,
        "weaponErgonomicPenalty": 0,
        "TemplateType": "gear"
    },
    "5a43957686f7742a2c2f11b0": {
        "ItemID": "5a43957686f7742a2c2f11b0",
        "Name": "cap_santa",
        "AllowADS": true,
        "LoyaltyLevel": 1,
        "ReloadSpeedMulti": 1,
        "BlocksMouth": false,
        "speedPenaltyPercent": 0,
        "mousePenalty": 0,
        "weaponErgonomicPenalty": 0,
        "TemplateType": "gear"
    },
    "5aa2ba46e5b5b000137b758d": {
        "ItemID": "5aa2ba46e5b5b000137b758d",
        "Name": "hats_UF_PRO",
        "AllowADS": true,
        "LoyaltyLevel": 3,
        "ReloadSpeedMulti": 1,
        "BlocksMouth": false,
        "speedPenaltyPercent": 0,
        "mousePenalty": 0,
        "weaponErgonomicPenalty": 0,
        "TemplateType": "gear"
    },
    "5bd073c986f7747f627e796c": {
        "ItemID": "5bd073c986f7747f627e796c",
        "Name": "item_equipment_head_kotton",
        "AllowADS": true,
        "LoyaltyLevel": 1,
        "ReloadSpeedMulti": 1,
        "BlocksMouth": false,
        "speedPenaltyPercent": 0,
        "mousePenalty": 0,
        "weaponErgonomicPenalty": 0,
        "TemplateType": "gear"
    },
    "60bf74184a63fc79b60c57f6": {
        "ItemID": "60bf74184a63fc79b60c57f6",
        "Name": "item_equipment_head_bomber",
        "AllowADS": true,
        "LoyaltyLevel": 4,
        "ReloadSpeedMulti": 1,
        "BlocksMouth": false,
        "speedPenaltyPercent": 0,
        "mousePenalty": 0,
        "weaponErgonomicPenalty": 0,
        "TemplateType": "gear"
    },
    "6040de02647ad86262233012": {
        "ItemID": "6040de02647ad86262233012",
        "Name": "item_equipment_head_military2_cadpat",
        "AllowADS": true,
        "LoyaltyLevel": 1,
        "ReloadSpeedMulti": 1,
        "BlocksMouth": false,
        "speedPenaltyPercent": 0,
        "mousePenalty": 0,
        "weaponErgonomicPenalty": 0,
        "TemplateType": "gear"
    },
    "60361a7497633951dc245eb4": {
        "ItemID": "60361a7497633951dc245eb4",
        "Name": "item_equipment_head_military2_flora",
        "AllowADS": true,
        "LoyaltyLevel": 1,
        "ReloadSpeedMulti": 1,
        "BlocksMouth": false,
        "speedPenaltyPercent": 0,
        "mousePenalty": 0,
        "weaponErgonomicPenalty": 0,
        "TemplateType": "gear"
    },
    "5b40e61f5acfc4001a599bec": {
        "ItemID": "5b40e61f5acfc4001a599bec",
        "Name": "item_equipment_head_usec_black",
        "AllowADS": true,
        "LoyaltyLevel": 2,
        "ReloadSpeedMulti": 1,
        "BlocksMouth": false,
        "speedPenaltyPercent": 0,
        "mousePenalty": 0,
        "weaponErgonomicPenalty": 0,
        "TemplateType": "gear"
    },
    "5c066ef40db834001966a595": {
        "ItemID": "5c066ef40db834001966a595",
        "Name": "helmet_armasight_nvg_googles_mask",
        "AllowADS": true,
        "LoyaltyLevel": 2,
        "ReloadSpeedMulti": 1,
        "BlocksMouth": false,
        "speedPenaltyPercent": 0,
        "mousePenalty": 0,
        "weaponErgonomicPenalty": 0,
        "TemplateType": "gear"
    },
    "5aa2b8d7e5b5b00014028f4a": {
        "ItemID": "5aa2b8d7e5b5b00014028f4a",
        "Name": "cap_police",
        "AllowADS": true,
        "LoyaltyLevel": 1,
        "ReloadSpeedMulti": 1,
        "BlocksMouth": false,
        "speedPenaltyPercent": 0,
        "mousePenalty": 0,
        "weaponErgonomicPenalty": 0,
        "TemplateType": "gear"
    },
    "5f994730c91ed922dd355de3": {
        "ItemID": "5f994730c91ed922dd355de3",
        "Name": "item_equipment_head_r2",
        "AllowADS": true,
        "LoyaltyLevel": 2,
        "ReloadSpeedMulti": 1,
        "BlocksMouth": false,
        "speedPenaltyPercent": 0,
        "mousePenalty": 0,
        "weaponErgonomicPenalty": 0,
        "TemplateType": "gear"
    },
    "618aef6d0a5a59657e5f55ee": {
        "ItemID": "618aef6d0a5a59657e5f55ee",
        "Name": "item_equipment_head_panama_jackpyke",
        "AllowADS": true,
        "LoyaltyLevel": 2,
        "ReloadSpeedMulti": 1,
        "BlocksMouth": false,
        "speedPenaltyPercent": 0,
        "mousePenalty": 0,
        "weaponErgonomicPenalty": 0,
        "TemplateType": "gear"
    },
    "60b52e5bc7d8103275739d67": {
        "ItemID": "60b52e5bc7d8103275739d67",
        "Name": "item_equipment_head_panama_stichprofi",
        "AllowADS": true,
        "LoyaltyLevel": 2,
        "ReloadSpeedMulti": 1,
        "BlocksMouth": false,
        "speedPenaltyPercent": 0,
        "mousePenalty": 0,
        "weaponErgonomicPenalty": 0,
        "TemplateType": "gear"
    },
    "636270263f2495c26f00b007": {
        "ItemID": "636270263f2495c26f00b007",
        "Name": "item_equipment_head_BOSS_zryachi_balaclava_open",
        "AllowADS": true,
        "LoyaltyLevel": 2,
        "ReloadSpeedMulti": 1,
        "BlocksMouth": false,
        "speedPenaltyPercent": 0,
        "mousePenalty": 0,
        "weaponErgonomicPenalty": 0,
        "TemplateType": "gear"
    },
    "628e4dd1f477aa12234918aa": {
        "ItemID": "628e4dd1f477aa12234918aa",
        "Name": "item_equipment_head_bandana_boss_Big_Pipe",
        "AllowADS": true,
        "LoyaltyLevel": 2,
        "ReloadSpeedMulti": 1,
        "BlocksMouth": false,
        "speedPenaltyPercent": 0,
        "mousePenalty": 0,
        "weaponErgonomicPenalty": 0,
        "TemplateType": "gear"
    },
    "603618feffd42c541047f771": {
        "ItemID": "603618feffd42c541047f771",
        "Name": "item_equipment_head_military2_black",
        "AllowADS": true,
        "LoyaltyLevel": 2,
        "ReloadSpeedMulti": 1,
        "BlocksMouth": false,
        "speedPenaltyPercent": 0,
        "mousePenalty": 0,
        "weaponErgonomicPenalty": 0,
        "TemplateType": "gear"
    },
    "60361b0b5a45383c122086a1": {
        "ItemID": "60361b0b5a45383c122086a1",
        "Name": "item_equipment_head_military2_sand",
        "AllowADS": true,
        "LoyaltyLevel": 2,
        "ReloadSpeedMulti": 1,
        "BlocksMouth": false,
        "speedPenaltyPercent": 0,
        "mousePenalty": 0,
        "weaponErgonomicPenalty": 0,
        "TemplateType": "gear"
    },
    "62a5c2c98ec41a51b34739c0": {
        "ItemID": "62a5c2c98ec41a51b34739c0",
        "Name": "item_equipment_facecover_hockey_01",
        "AllowADS": true,
        "LoyaltyLevel": 2,
        "ReloadSpeedMulti": 1,
        "BlocksMouth": true,
        "speedPenaltyPercent": -5,
        "mousePenalty": 0,
        "weaponErgonomicPenalty": -10,
        "TemplateType": "gear"
    },
    "62a5c333ec21e50cad3b5dc6": {
        "ItemID": "62a5c333ec21e50cad3b5dc6",
        "Name": "item_equipment_facecover_hockey_02",
        "AllowADS": true,
        "LoyaltyLevel": 2,
        "ReloadSpeedMulti": 1,
        "BlocksMouth": true,
        "speedPenaltyPercent": -5,
        "mousePenalty": 0,
        "weaponErgonomicPenalty": -10,
        "TemplateType": "gear"
    },
    "62a5c41e8ec41a51b34739c3": {
        "ItemID": "62a5c41e8ec41a51b34739c3",
        "Name": "item_equipment_facecover_hockey_03",
        "AllowADS": true,
        "LoyaltyLevel": 2,
        "ReloadSpeedMulti": 1,
        "BlocksMouth": true,
        "speedPenaltyPercent": -5,
        "mousePenalty": 0,
        "weaponErgonomicPenalty": -10,
        "TemplateType": "gear"
    },
    "62963c18dbc8ab5f0d382d0b": {
        "ItemID": "62963c18dbc8ab5f0d382d0b",
        "Name": "item_equipment_facecover_mask_boss_blackknight",
        "AllowADS": true,
        "LoyaltyLevel": 4,
        "ReloadSpeedMulti": 1,
        "BlocksMouth": false,
        "speedPenaltyPercent": 0,
        "mousePenalty": 0,
        "weaponErgonomicPenalty": 0,
        "TemplateType": "gear"
    },
    "5e54f79686f7744022011103": {
        "ItemID": "5e54f79686f7744022011103",
        "Name": "item_equipment_facecover_pestily",
        "AllowADS": true,
        "LoyaltyLevel": 4,
        "ReloadSpeedMulti": 1,
        "BlocksMouth": true,
        "speedPenaltyPercent": -10,
        "mousePenalty": 0,
        "weaponErgonomicPenalty": -10,
        "TemplateType": "gear"
    },
    "5b432b6c5acfc4001a599bf0": {
        "ItemID": "5b432b6c5acfc4001a599bf0",
        "Name": "item_equipment_facecover_skullmask",
        "AllowADS": true,
        "LoyaltyLevel": 1,
        "ReloadSpeedMulti": 1,
        "BlocksMouth": true,
        "speedPenaltyPercent": -5,
        "mousePenalty": 0,
        "weaponErgonomicPenalty": -10,
        "TemplateType": "gear"
    },
    "59e7715586f7742ee5789605": {
        "ItemID": "59e7715586f7742ee5789605",
        "Name": "respirator_3m",
        "AllowADS": true,
        "LoyaltyLevel": 1,
        "ReloadSpeedMulti": 1,
        "BlocksMouth": true,
        "speedPenaltyPercent": -30,
        "mousePenalty": 0,
        "weaponErgonomicPenalty": -10,
        "TemplateType": "gear"
    },
    "5bd071d786f7747e707b93a3": {
        "ItemID": "5bd071d786f7747e707b93a3",
        "Name": "item_equipment_facecover_HALLOWEEN_Jason",
        "AllowADS": true,
        "LoyaltyLevel": 4,
        "ReloadSpeedMulti": 1,
        "BlocksMouth": true,
        "speedPenaltyPercent": -5,
        "mousePenalty": 0,
        "weaponErgonomicPenalty": -10,
        "TemplateType": "gear"
    },
    "5bd0716d86f774171822ef4b": {
        "ItemID": "5bd0716d86f774171822ef4b",
        "Name": "item_equipment_facecover_HALLOWEEN_Micheal",
        "AllowADS": true,
        "LoyaltyLevel": 4,
        "ReloadSpeedMulti": 1,
        "BlocksMouth": true,
        "speedPenaltyPercent": -5,
        "mousePenalty": 0,
        "weaponErgonomicPenalty": -10,
        "TemplateType": "gear"
    },
    "5bd06f5d86f77427101ad47c": {
        "ItemID": "5bd06f5d86f77427101ad47c",
        "Name": "item_equipment_facecover_HALLOWEEN_Slander",
        "AllowADS": true,
        "LoyaltyLevel": 4,
        "ReloadSpeedMulti": 1,
        "BlocksMouth": true,
        "speedPenaltyPercent": -5,
        "mousePenalty": 0,
        "weaponErgonomicPenalty": -10,
        "TemplateType": "gear"
    },
    "62a09dd4621468534a797ac7": {
        "ItemID": "62a09dd4621468534a797ac7",
        "Name": "item_equipment_facecover_beard_red",
        "AllowADS": true,
        "LoyaltyLevel": 2,
        "ReloadSpeedMulti": 1,
        "BlocksMouth": false,
        "speedPenaltyPercent": 0,
        "mousePenalty": 0,
        "weaponErgonomicPenalty": 0,
        "TemplateType": "gear"
    },
    "5b432c305acfc40019478128": {
        "ItemID": "5b432c305acfc40019478128",
        "Name": "item_equipment_facecover_gasmask_GP5",
        "AllowADS": true,
        "LoyaltyLevel": 2,
        "ReloadSpeedMulti": 1,
        "BlocksMouth": true,
        "speedPenaltyPercent": -30,
        "mousePenalty": 0,
        "weaponErgonomicPenalty": -6,
        "TemplateType": "gear"
    },
    "60363c0c92ec1c31037959f5": {
        "ItemID": "60363c0c92ec1c31037959f5",
        "Name": "item_equipment_facecover_gasmask_gp7",
        "AllowADS": true,
        "LoyaltyLevel": 3,
        "ReloadSpeedMulti": 1,
        "BlocksMouth": true,
        "speedPenaltyPercent": -25,
        "mousePenalty": 0,
        "weaponErgonomicPenalty": -4,
        "TemplateType": "gear"
    },
    "62a09e08de7ac81993580532": {
        "ItemID": "62a09e08de7ac81993580532",
        "Name": "item_equipment_facecover_glorious",
        "AllowADS": true,
        "LoyaltyLevel": 4,
        "ReloadSpeedMulti": 1,
        "BlocksMouth": true,
        "speedPenaltyPercent": 0,
        "mousePenalty": 0,
        "weaponErgonomicPenalty": 0,
        "TemplateType": "gear"
    },
    "6176a48d732a664031271438": {
        "ItemID": "6176a48d732a664031271438",
        "Name": "item_equipment_facecover_halloween_kaonasi",
        "AllowADS": true,
        "LoyaltyLevel": 4,
        "ReloadSpeedMulti": 1,
        "BlocksMouth": true,
        "speedPenaltyPercent": -5,
        "mousePenalty": 0,
        "weaponErgonomicPenalty": -10,
        "TemplateType": "gear"
    },
    "635267ab3c89e2112001f826": {
        "ItemID": "635267ab3c89e2112001f826",
        "Name": "item_equipment_facecover_halloween_skull",
        "AllowADS": true,
        "LoyaltyLevel": 4,
        "ReloadSpeedMulti": 1,
        "BlocksMouth": true,
        "speedPenaltyPercent": -5,
        "mousePenalty": 0,
        "weaponErgonomicPenalty": -10,
        "TemplateType": "gear"
    },
    "6176a40f0b8c0312ac75a3d3": {
        "ItemID": "6176a40f0b8c0312ac75a3d3",
        "Name": "item_equipment_facecover_halloween_vampire",
        "AllowADS": true,
        "LoyaltyLevel": 4,
        "ReloadSpeedMulti": 1,
        "BlocksMouth": true,
        "speedPenaltyPercent": -5,
        "mousePenalty": 0,
        "weaponErgonomicPenalty": -10,
        "TemplateType": "gear"
    },
    "572b7f1624597762ae139822": {
        "ItemID": "572b7f1624597762ae139822",
        "Name": "balaclava",
        "AllowADS": true,
        "LoyaltyLevel": 1,
        "ReloadSpeedMulti": 1,
        "BlocksMouth": false,
        "speedPenaltyPercent": 0,
        "mousePenalty": 0,
        "weaponErgonomicPenalty": 0,
        "TemplateType": "gear"
    },
    "5ab8f39486f7745cd93a1cca": {
        "ItemID": "5ab8f39486f7745cd93a1cca",
        "Name": "balaclava_cg",
        "AllowADS": true,
        "LoyaltyLevel": 4,
        "ReloadSpeedMulti": 1,
        "BlocksMouth": false,
        "speedPenaltyPercent": 0,
        "mousePenalty": 0,
        "weaponErgonomicPenalty": 0,
        "TemplateType": "gear"
    },
    "5ab8f4ff86f77431c60d91ba": {
        "ItemID": "5ab8f4ff86f77431c60d91ba",
        "Name": "balaclava_skull",
        "AllowADS": true,
        "LoyaltyLevel": 5,
        "ReloadSpeedMulti": 1,
        "BlocksMouth": false,
        "speedPenaltyPercent": 0,
        "mousePenalty": 0,
        "weaponErgonomicPenalty": 0,
        "TemplateType": "gear"
    },
    "5c1a1e3f2e221602b66cc4c2": {
        "ItemID": "5c1a1e3f2e221602b66cc4c2",
        "Name": "item_beard",
        "AllowADS": true,
        "LoyaltyLevel": 2,
        "ReloadSpeedMulti": 1,
        "BlocksMouth": false,
        "speedPenaltyPercent": 0,
        "mousePenalty": 0,
        "weaponErgonomicPenalty": 0,
        "TemplateType": "gear"
    },
    "63626d904aa74b8fe30ab426": {
        "ItemID": "63626d904aa74b8fe30ab426",
        "Name": "item_equipment_facecover_BOSS_zryachi_balaclava_closed",
        "AllowADS": true,
        "LoyaltyLevel": 4,
        "ReloadSpeedMulti": 1,
        "BlocksMouth": false,
        "speedPenaltyPercent": 0,
        "mousePenalty": 0,
        "weaponErgonomicPenalty": 0,
        "TemplateType": "gear"
    },
    "607f201b3c672b3b3a24a800": {
        "ItemID": "607f201b3c672b3b3a24a800",
        "Name": "item_equipment_facecover_coldgear_twitch",
        "AllowADS": true,
        "LoyaltyLevel": 4,
        "ReloadSpeedMulti": 1,
        "BlocksMouth": false,
        "speedPenaltyPercent": 0,
        "mousePenalty": 0,
        "weaponErgonomicPenalty": 0,
        "TemplateType": "gear"
    },
    "5b432f3d5acfc4704b4a1dfb": {
        "ItemID": "5b432f3d5acfc4704b4a1dfb",
        "Name": "item_equipment_facecover_nomexBalaclava",
        "AllowADS": true,
        "LoyaltyLevel": 4,
        "ReloadSpeedMulti": 1,
        "BlocksMouth": false,
        "speedPenaltyPercent": 0,
        "mousePenalty": 0,
        "weaponErgonomicPenalty": 0,
        "TemplateType": "gear"
    },
    "62a61bbf8ec41a51b34758d2": {
        "ItemID": "62a61bbf8ec41a51b34758d2",
        "Name": "item_equipment_facecover_pipe",
        "AllowADS": true,
        "LoyaltyLevel": 4,
        "ReloadSpeedMulti": 1,
        "BlocksMouth": false,
        "speedPenaltyPercent": 0,
        "mousePenalty": 0,
        "weaponErgonomicPenalty": 0,
        "TemplateType": "gear"
    },
    "5b4326435acfc433000ed01d": {
        "ItemID": "5b4326435acfc433000ed01d",
        "Name": "item_equipment_facecover_redflame",
        "AllowADS": true,
        "LoyaltyLevel": 4,
        "ReloadSpeedMulti": 1,
        "BlocksMouth": false,
        "speedPenaltyPercent": 0,
        "mousePenalty": 0,
        "weaponErgonomicPenalty": 0,
        "TemplateType": "gear"
    },
    "5e71f6be86f77429f2683c44": {
        "ItemID": "5e71f6be86f77429f2683c44",
        "Name": "item_equipment_facecover_redflame_twitch",
        "AllowADS": true,
        "LoyaltyLevel": 4,
        "ReloadSpeedMulti": 1,
        "BlocksMouth": false,
        "speedPenaltyPercent": 0,
        "mousePenalty": 0,
        "weaponErgonomicPenalty": 0,
        "TemplateType": "gear"
    },
    "5b4325355acfc40019478126": {
        "ItemID": "5b4325355acfc40019478126",
        "Name": "item_equipment_facecover_shemagh_02",
        "AllowADS": true,
        "LoyaltyLevel": 3,
        "ReloadSpeedMulti": 1,
        "BlocksMouth": false,
        "speedPenaltyPercent": 0,
        "mousePenalty": 0,
        "weaponErgonomicPenalty": 0,
        "TemplateType": "gear"
    },
    "5e54f76986f7740366043752": {
        "ItemID": "5e54f76986f7740366043752",
        "Name": "item_equipment_facecover_shroud",
        "AllowADS": true,
        "LoyaltyLevel": 4,
        "ReloadSpeedMulti": 1,
        "BlocksMouth": false,
        "speedPenaltyPercent": 0,
        "mousePenalty": 0,
        "weaponErgonomicPenalty": 0,
        "TemplateType": "gear"
    },
    "5fd8d28367cb5e077335170f": {
        "ItemID": "5fd8d28367cb5e077335170f",
        "Name": "item_equipment_facecover_smoke",
        "AllowADS": true,
        "LoyaltyLevel": 4,
        "ReloadSpeedMulti": 1,
        "BlocksMouth": false,
        "speedPenaltyPercent": 0,
        "mousePenalty": 0,
        "weaponErgonomicPenalty": 0,
        "TemplateType": "gear"
    },
    "5e71fad086f77422443d4604": {
        "ItemID": "5e71fad086f77422443d4604",
        "Name": "item_equipment_facecover_twitch",
        "AllowADS": true,
        "LoyaltyLevel": 4,
        "ReloadSpeedMulti": 1,
        "BlocksMouth": false,
        "speedPenaltyPercent": 0,
        "mousePenalty": 0,
        "weaponErgonomicPenalty": 0,
        "TemplateType": "gear"
    },
    "5bd073a586f7747e6f135799": {
        "ItemID": "5bd073a586f7747e6f135799",
        "Name": "item_equipment_mustache",
        "AllowADS": true,
        "LoyaltyLevel": 4,
        "ReloadSpeedMulti": 1,
        "BlocksMouth": false,
        "speedPenaltyPercent": 0,
        "mousePenalty": 0,
        "weaponErgonomicPenalty": 0,
        "TemplateType": "gear"
    },
    "572b7fa524597762b747ce82": {
        "ItemID": "572b7fa524597762b747ce82",
        "Name": "mask",
        "AllowADS": true,
        "LoyaltyLevel": 2,
        "ReloadSpeedMulti": 1,
        "BlocksMouth": false,
        "speedPenaltyPercent": 0,
        "mousePenalty": 0,
        "weaponErgonomicPenalty": 0,
        "TemplateType": "gear"
    },
    "5ab8f85d86f7745cd93a1cf5": {
        "ItemID": "5ab8f85d86f7745cd93a1cf5",
        "Name": "shemagh",
        "AllowADS": true,
        "LoyaltyLevel": 3,
        "ReloadSpeedMulti": 1,
        "BlocksMouth": false,
        "speedPenaltyPercent": 0,
        "mousePenalty": 0,
        "weaponErgonomicPenalty": 0,
        "TemplateType": "gear"
    }
}