{
    "5d1b5e94d7ad1a2b865a96b0": {
        "ID": "5d1b5e94d7ad1a2b865a96b0",
        "ModType": "",
        "VerticalRecoil": 0,
        "HorizontalRecoil": 0,
        "Dispersion": 0,
        "CameraRecoil": 0,
        "AutoROF": 0,
        "SemiROF": 0,
        "MalfunctionChance": 0,
        "ReloadSpeed": 0,
        "AimSpeed": 0,
        "DrawSpeed": 0,
        "Length": 0,
        "CanCylceSubs": false
    },
    "609bab8b455afd752b2e6138": {
        "ID": "609bab8b455afd752b2e6138",
        "ModType": "",
        "VerticalRecoil": 0,
        "HorizontalRecoil": 0,
        "Dispersion": 0,
        "CameraRecoil": 0,
        "AutoROF": 0,
        "SemiROF": 0,
        "MalfunctionChance": 0,
        "ReloadSpeed": 0,
        "AimSpeed": 0,
        "DrawSpeed": 0,
        "Length": 0,
        "CanCylceSubs": false
    },
    "5b3b6e495acfc4330140bd88": {
        "ID": "5b3b6e495acfc4330140bd88",
        "ModType": "",
        "VerticalRecoil": 0,
        "HorizontalRecoil": 0,
        "Dispersion": 0,
        "CameraRecoil": 0,
        "AutoROF": 0,
        "SemiROF": 0,
        "MalfunctionChance": 0,
        "ReloadSpeed": 0,
        "AimSpeed": 0,
        "DrawSpeed": 0,
        "Length": 0,
        "CanCylceSubs": false
    },
    "5a1eaa87fcdbcb001865f75e": {
        "ID": "5a1eaa87fcdbcb001865f75e",
        "ModType": "",
        "VerticalRecoil": 0,
        "HorizontalRecoil": 0,
        "Dispersion": 0,
        "CameraRecoil": 0,
        "AutoROF": 0,
        "SemiROF": 0,
        "MalfunctionChance": 0,
        "ReloadSpeed": 0,
        "AimSpeed": 0,
        "DrawSpeed": 0,
        "Length": 0,
        "CanCylceSubs": false
    },
    "5a7c74b3e899ef0014332c29": {
        "ID": "5a7c74b3e899ef0014332c29",
        "ModType": "",
        "VerticalRecoil": -2.5,
        "HorizontalRecoil": -2.5,
        "Dispersion": 0,
        "CameraRecoil": 0,
        "AutoROF": 0,
        "SemiROF": 0,
        "MalfunctionChance": 0,
        "ReloadSpeed": 0,
        "AimSpeed": 0,
        "DrawSpeed": 0,
        "Length": 0,
        "CanCylceSubs": false
    },
    "606f2696f2cb2e02a42aceb1": {
        "ID": "606f2696f2cb2e02a42aceb1",
        "ModType": "",
        "VerticalRecoil": 0,
        "HorizontalRecoil": 0,
        "Dispersion": 0,
        "CameraRecoil": 0,
        "AutoROF": 0,
        "SemiROF": 0,
        "MalfunctionChance": 0,
        "ReloadSpeed": 0,
        "AimSpeed": 0,
        "DrawSpeed": 0,
        "Length": 0,
        "CanCylceSubs": false
    }
}